sxpy/__init__.py
sxpy/core/compiler/__init__.py
sxpy/core/compiler/expr.py
sxpy/core/compiler/literal.py
sxpy/core/compiler/stmt.py
sxpy/core/compiler/utils.py
sxpy/core/importer.py
sxpy/core/macro.py
sxpy/core/meta_functions.py
sxpy/core/nodes.py
sxpy/core/parser.py
sxpy/core/utils.py
sxpy/core_meta_functions.sy
sxpy/macros/__init__.py
sxpy/macros/init.sy
sxpy/macros/sugar.sy
sxpy/tools.sy
sexypy-0.7.3.dist-info/LICENSE.md
sexypy-0.7.3.dist-info/METADATA
sexypy-0.7.3.dist-info/WHEEL
sexypy-0.7.3.dist-info/entry_points.txt
sexypy-0.7.3.dist-info/RECORD
