Metadata-Version: 2.1
Name: sexypy
Version: 0.7.3
Summary: Python with S-expression Grammar
Home-page: https://jethack23.github.io/sexypy
License: MIT
Author: Jethack
Author-email: jethack23@gmail.com
Requires-Python: >=3.11,<3.12
Classifier: License :: OSI Approved :: MIT License
Classifier: Programming Language :: Python :: 3
Classifier: Programming Language :: Python :: 3.11
Project-URL: Repository, https://github.com/jethack23/sexypy
